qtpy/Qsci.py
qtpy/Qt3DAnimation.py
qtpy/Qt3DCore.py
qtpy/Qt3DExtras.py
qtpy/Qt3DInput.py
qtpy/Qt3DLogic.py
qtpy/Qt3DRender.py
qtpy/QtAxContainer.py
qtpy/QtBluetooth.py
qtpy/QtCharts.py
qtpy/QtConcurrent.py
qtpy/QtCore.py
qtpy/QtDBus.py
qtpy/QtDataVisualization.py
qtpy/QtDesigner.py
qtpy/QtGui.py
qtpy/QtHelp.py
qtpy/QtLocation.py
qtpy/QtMacExtras.py
qtpy/QtMultimedia.py
qtpy/QtMultimediaWidgets.py
qtpy/QtNetwork.py
qtpy/QtNetworkAuth.py
qtpy/QtNfc.py
qtpy/QtOpenGL.py
qtpy/QtOpenGLWidgets.py
qtpy/QtPdf.py
qtpy/QtPdfWidgets.py
qtpy/QtPositioning.py
qtpy/QtPrintSupport.py
qtpy/QtPurchasing.py
qtpy/QtQml.py
qtpy/QtQuick.py
qtpy/QtQuick3D.py
qtpy/QtQuickControls2.py
qtpy/QtQuickWidgets.py
qtpy/QtRemoteObjects.py
qtpy/QtScxml.py
qtpy/QtSensors.py
qtpy/QtSerialPort.py
qtpy/QtSql.py
qtpy/QtStateMachine.py
qtpy/QtSvg.py
qtpy/QtSvgWidgets.py
qtpy/QtTest.py
qtpy/QtTextToSpeech.py
qtpy/QtUiTools.py
qtpy/QtWebChannel.py
qtpy/QtWebEngine.py
qtpy/QtWebEngineCore.py
qtpy/QtWebEngineQuick.py
qtpy/QtWebEngineWidgets.py
qtpy/QtWebSockets.py
qtpy/QtWidgets.py
qtpy/QtWinExtras.py
qtpy/QtX11Extras.py
qtpy/QtXml.py
qtpy/QtXmlPatterns.py
qtpy/__init__.py
qtpy/__main__.py
qtpy/_utils.py
qtpy/cli.py
qtpy/compat.py
qtpy/enums_compat.py
qtpy/py.typed
qtpy/shiboken.py
qtpy/sip.py
qtpy/uic.py
qtpy/tests/__init__.py
qtpy/tests/conftest.py
qtpy/tests/test.ui
qtpy/tests/test_cli.py
qtpy/tests/test_compat.py
qtpy/tests/test_custom.ui
qtpy/tests/test_macos_checks.py
qtpy/tests/test_main.py
qtpy/tests/test_missing_optional_deps.py
qtpy/tests/test_qdesktopservice_split.py
qtpy/tests/test_qsci.py
qtpy/tests/test_qt3danimation.py
qtpy/tests/test_qt3dcore.py
qtpy/tests/test_qt3dextras.py
qtpy/tests/test_qt3dinput.py
qtpy/tests/test_qt3dlogic.py
qtpy/tests/test_qt3drender.py
qtpy/tests/test_qtaxcontainer.py
qtpy/tests/test_qtbluetooth.py
qtpy/tests/test_qtcharts.py
qtpy/tests/test_qtconcurrent.py
qtpy/tests/test_qtcore.py
qtpy/tests/test_qtdatavisualization.py
qtpy/tests/test_qtdbus.py
QtPy-2.4.2.dist-info/AUTHORS.md
QtPy-2.4.2.dist-info/LICENSE.txt
QtPy-2.4.2.dist-info/METADATA
QtPy-2.4.2.dist-info/WHEEL
QtPy-2.4.2.dist-info/entry_points.txt
QtPy-2.4.2.dist-info/top_level.txt
QtPy-2.4.2.dist-info/RECORD
