Metadata-Version: 2.1
Name: QtPy
Version: 2.4.2
Summary: Provides an abstraction layer on top of the various Qt bindings (PyQt5/6 and PySide2/6).
Home-page: https://github.com/spyder-ide/qtpy
Author: Colin Duquesnoy and the Spyder Development Team
Author-email: spyder.python@gmail.com
Maintainer: Spyder Development Team and QtPy Contributors
Maintainer-email: spyder.python@gmail.com
License: MIT
Project-URL: Github, https://github.com/spyder-ide/qtpy
Project-URL: Bug Tracker, https://github.com/spyder-ide/qtpy/issues
Project-URL: Parent Project, https://www.spyder-ide.org/
Keywords: qt PyQt5 PyQt6 PySide2 PySide6
Classifier: Development Status :: 5 - Production/Stable
Classifier: Environment :: MacOS X
Classifier: Environment :: Win32 (MS Windows)
Classifier: Environment :: X11 Applications :: Qt
Classifier: Intended Audience :: Developers
Classifier: License :: OSI Approved :: MIT License
Classifier: Operating System :: OS Independent
Classifier: Programming Language :: Python :: 3
Classifier: Programming Language :: Python :: 3 :: Only
Classifier: Programming Language :: Python :: 3.7
Classifier: Programming Language :: Python :: 3.8
Classifier: Programming Language :: Python :: 3.9
Classifier: Programming Language :: Python :: 3.10
Classifier: Programming Language :: Python :: 3.11
Classifier: Topic :: Software Development :: Libraries
Classifier: Topic :: Software Development :: User Interfaces
Classifier: Topic :: Software Development :: Widget Sets
Requires-Python: >=3.7
License-File: AUTHORS.md
License-File: LICENSE.txt
Requires-Dist: packaging
Provides-Extra: test
Requires-Dist: pytest!=7.0.0,!=7.0.1,>=6; extra == "test"
Requires-Dist: pytest-cov>=3.0.0; extra == "test"
Requires-Dist: pytest-qt; extra == "test"
